inventarium.py
Inventarium-1.0.dist-info/DESCRIPTION.rst
Inventarium-1.0.dist-info/METADATA
Inventarium-1.0.dist-info/RECORD
Inventarium-1.0.dist-info/WHEEL
Inventarium-1.0.dist-info/entry_points.txt
Inventarium-1.0.dist-info/metadata.json
Inventarium-1.0.dist-info/top_level.txt
